{"cameraMode":{"drawMode":0,"name":"Shaded","section":"Shading Mode"},"sceneLighting":true,"audioPlay":false,"sceneViewState":{"showFog":true,"showMaterialUpdate":false,"showSkybox":true,"showFlares":true,"showImageEffects":true,"showParticleSystems":true},"in2DMode":false,"pivot":{"x":10.963608741760254,"y":-1.5908279418945313,"z":2.2182226181030275},"rotation":{"x":0.6930707693099976,"y":-0.01382470317184925,"z":0.013296158984303475,"w":0.7206412553787231},"size":21.656417846679689,"orthographic":false}